haversine/__init__.py
haversine/haversine.py
tests/__init__.py
tests/test_haversine.py
aversine-0.0.1.dist-info/LICENSE
aversine-0.0.1.dist-info/METADATA
aversine-0.0.1.dist-info/WHEEL
aversine-0.0.1.dist-info/top_level.txt
aversine-0.0.1.dist-info/RECORD
