Metadata-Version: 2.1
Name: aversine
Version: 0.0.1
Summary: Python implementation of haversine formula to determine the
Home-page: https://github.com/ajepe/haversine
Author: Babatope Ajepe
Author-email: babatopeajepe@gmail.com
License: UNKNOWN
Platform: UNKNOWN
Classifier: Programming Language :: Python :: 3
Classifier: License :: OSI Approved :: MIT License
Classifier: Operating System :: OS Independent
